pyproxyauth-0.3.0.dist-info/METADATA
pyproxyauth-0.3.0.dist-info/WHEEL
pyproxyauth.libs/libcrypto-8bcb947c.so.3
pyproxyauth.libs/libssl-9e2b5710.so.3
pyproxyauth/__init__.py
pyproxyauth/pyproxyauth.cpython-312-x86_64-linux-gnu.so
pyproxyauth-0.3.0.dist-info/RECORD
