Metadata-Version: 2.4
Name: pyproxyauth
Version: 0.3.0
Classifier: Programming Language :: Python :: 3
Classifier: Programming Language :: Rust
Classifier: Operating System :: OS Independent
Classifier: Topic :: Internet :: Proxy Servers
Classifier: Topic :: Software Development :: Libraries :: Python Modules
Classifier: Intended Audience :: Developers
Summary: Python bindings for ProxyAuth authentication via Rust
Author: vBlackOut
License: Apache-2.0
Requires-Python: >=3.7
